{"data":[{"name":"33:33","price":"你们应当安居于你们的家中，你们不要炫露你们的美丽，如从前蒙昧时代的妇女那样。你们应当谨守拜功，完纳天课，顺从安拉及其使者。先知的家属啊！安拉只欲消除你们的污秽，洗净你们的罪恶。","arabic":"وَقَرۡنَ فِي بُيُوتِكُنَّ وَلَا تَبَرَّجۡنَ تَبَرُّجَ ٱلۡجَٰهِلِيَّةِ ٱلۡأُولَىٰۖ وَأَقِمۡنَ ٱلصَّلَوٰةَ وَءَاتِينَ ٱلزَّكَوٰةَ وَأَطِعۡنَ ٱللَّهَ وَرَسُولَهُۥٓۚ إِنَّمَا يُرِيدُ ٱللَّهُ لِيُذۡهِبَ عَنكُمُ ٱلرِّجۡسَ أَهۡلَ ٱلۡبَيۡتِ وَيُطَهِّرَكُمۡ تَطۡهِيرٗا","category":["33 (Al-Ahzab)","Al-Ahzab","Surah Al-Ahzab"],"ayahNumber":3566,"juzNumber":22,"footnotes":"","lang":"zh","meta":{"transliteration":"waqarna fī buyūtikunna walā tabarrajna tabarruja al-jāhiliyati al-ūlā wa-aqim'na al-ṣalata waātīna al-zakata wa-aṭiʿ'na al-laha warasūlahu innamā yurīdu al-lahu liyudh'hiba ʿankumu al-rij'sa ahla al-bayti wayuṭahhirakum taṭhīran ","translations":["And stay","in","your houses","and (do) not","display yourselves","(as was the) display","(of the times of) ignorance","the former","And establish","the prayer","and give","zakah","and obey","Allah","and His Messenger","Only","Allah wishes","Allah wishes","to remove","from you","the impurity","(O) People","(of) the House","And to purify you","(with thorough) purification","(33)"],"transliterationArr":["waqarna","fī","buyūtikunna","walā","tabarrajna","tabarruja","al-jāhiliyati","al-ūlā","wa-aqim'na","al-ṣalata","waātīna","al-zakata","wa-aṭiʿ'na","al-laha","warasūlahu","innamā","yurīdu","al-lahu","liyudh'hiba","ʿankumu","al-rij'sa","ahla","al-bayti","wayuṭahhirakum","taṭhīran",null],"verseTiming":[[1,0,740],[2,740,1220],[3,1220,3390],[4,3390,3900],[5,3900,5040],[6,5040,6020],[7,6020,7680],[8,7680,8500],[9,8500,9500],[10,9500,11900],[11,11900,13180],[12,13180,14200],[13,14200,15250],[14,15250,16360],[15,16360,17210],[16,17210,18110],[17,18110,19660],[18,19660,21290],[19,21290,22110],[20,22110,22910],[21,22910,23890],[22,23890,25100],[23,25100,25940],[24,25940,26350],[25,26350,27280],[26,27280,28790],[27,28790,30485]]}}],"dua":{"id":69,"name":"Ayat al-Tathir","arabicName":"آية التطهير","reference":"33:33","verseTitle":"The Verse of Purification","significanceReason":"Emphasizes spiritual purification of the Prophet's household (Ahl al-Bayt), highlighting divine selection and spiritual cleansing. Significant in both theological and spiritual interpretations."},"version":{"key":"chinese_suliman","direction":"ltr","language_iso_code":"zh","version":"1.0.5","last_update":1710761004,"title":"Chinese Translation - Mohammed Suleiman","description":"Translation of the Qur’an meanings into Chinese, translated by Mohammed Makin, reviewed by Mohammed Suleiman with other specialists."}}