{"data":[{"name":"2:186","price":"૧૮૬- (અને હે નબી !)જ્યારે મારા બંદાઓ મારા વિશે તમારાથી સવાલ કરે તો તમે કહી દો કે હું ઘણો જ નજીક છું, દરેક પોકારવાવાળાની પોકારને જ્યારે પણ તે મને પોકારે, હું તેની પોકારને કબૂલ કરું છું, એટલા માટે તેઓ મારો આદેશ માને અને મારા પર જ ઇમાન ધરાવે, આશા છે કે તેઓ હિદાયત મેળવી લે.","arabic":"وَإِذَا سَأَلَكَ عِبَادِي عَنِّي فَإِنِّي قَرِيبٌۖ أُجِيبُ دَعۡوَةَ ٱلدَّاعِ إِذَا دَعَانِۖ فَلۡيَسۡتَجِيبُواْ لِي وَلۡيُؤۡمِنُواْ بِي لَعَلَّهُمۡ يَرۡشُدُونَ","category":["2 (Al-Baqarah)","Al-Baqarah","Surah Al-Baqarah"],"ayahNumber":193,"juzNumber":2,"footnotes":"","lang":"gu","meta":{"transliteration":"wa-idhā sa-alaka ʿibādī ʿannī fa-innī qarībun ujību daʿwata al-dāʿi idhā daʿāni falyastajībū lī walyu'minū bī laʿallahum yarshudūna ","translations":["And when","ask you","My servants","about Me","then indeed I am","near","I respond","(to the) invocation","(of) the supplicant","when","he calls Me","So let them respond","to Me","and let them believe","in Me","so that they may","(be) led aright","(186)"],"transliterationArr":["wa-idhā","sa-alaka","ʿibādī","ʿannī","fa-innī","qarībun","ujību","daʿwata","al-dāʿi","idhā","daʿāni","falyastajībū","lī","walyu'minū","bī","laʿallahum","yarshudūna",null],"verseTiming":[[1,0,910],[2,910,1730],[3,1730,2690],[4,2690,4130],[5,4130,5790],[6,5790,8670],[7,8670,9350],[8,9350,10130],[9,10130,10950],[10,10950,11500],[11,11500,14190],[12,14190,16260],[13,16260,16850],[14,16850,18250],[15,18250,18710],[16,18710,19870],[17,19870,23185]]}}],"dua":{"id":31,"name":"Dua for Divine Connection","arabicName":"دعاء الاتصال الإلهي","reference":"2:186","verseTitle":"The Intimate Supplication","significanceReason":"Emphasizes the direct and intimate connection between the believer and the Divine, highlighting that Allah is always near and responsive."},"version":{"key":"gujarati_omari","direction":"ltr","language_iso_code":"gu","version":"1.1.1","last_update":1706601566,"title":"Gujarati translation","description":"Translation of the Quran meanings into Gujarati by Rabila Al-Umry, published by Birr Institution - Mumbai 2017."}}